homa/__init__.py
homa/camera.py
homa/constants.py
homa/events.py
homa/filters.py
homa/helpers.py
homa/main.py
homa/orientation.py
homa/shapes.py
homa/spaces.py
homa/classes/Collection.py
homa/classes/Image.py
homa/classes/Logger.py
homa/classes/Repository.py
homa/classes/Window.py
homa/classes/__init__.py
homa/helpers/__init__.py
homa/helpers/alias.py
homa/helpers/environment.py
homa/helpers/kernel.py
homa/helpers/string.py
tests/__init__.py
tests/test_images.py
homa-0.26.dist-info/LICENSE
homa-0.26.dist-info/METADATA
homa-0.26.dist-info/WHEEL
homa-0.26.dist-info/top_level.txt
homa-0.26.dist-info/RECORD
