Metadata-Version: 2.1
Name: homa
Version: 0.26
Maintainer: Taha Shieenavaz
Maintainer-email: tahashieenavaz@gmail.com
License-File: LICENSE
Requires-Dist: opencv-python
Requires-Dist: numpy
